ringattention/__init__.py
ringattention/ringattention_inference.py
ringattention/ringattention_jax.py
ringattention/ringattention_pallas_gpu.py
ringattention/ringattention_pallas_tpu.py
ringattention-0.1.2.dist-info/LICENSE
ringattention-0.1.2.dist-info/METADATA
ringattention-0.1.2.dist-info/WHEEL
ringattention-0.1.2.dist-info/top_level.txt
ringattention-0.1.2.dist-info/RECORD
